{
  "generatedAt": "2026-02-20T16:03:55.916Z",
  "mode": "PROTECT",
  "nsi": 100,
  "trend": {
    "direction": "flat",
    "delta": 0
  },
  "counts": {
    "basesImpacted": 35,
    "nowCrit": 10,
    "nowHigh": 40,
    "nowMed": 39,
    "metCrit": 0,
    "tafCrit": 5,
    "engIceOpsCount": 0,
    "watchlistAirports": 159,
    "metarReturned": 159,
    "tafReturned": 158,
    "missingMetar": 0,
    "missingTaf": 1
  },
  "top": {
    "now": [
      "BBU",
      "OTP",
      "BLL",
      "AES",
      "BGO",
      "OSL",
      "KRK",
      "MMX"
    ],
    "forecast": [
      "BBU",
      "OTP",
      "BLL",
      "KSC",
      "TSR"
    ]
  },
  "drivers": {
    "vis": 63,
    "wind": 47,
    "snow": 37,
    "icing": 0,
    "ts": 21
  },
  "details": {
    "baseTags": {
      "BBU": [
        "snow",
        "vis"
      ],
      "OTP": [
        "snow",
        "vis"
      ],
      "KRK": [
        "snow",
        "vis"
      ],
      "BEG": [
        "snow",
        "vis"
      ],
      "TSR": [
        "vis"
      ],
      "TIA": [],
      "FCO": [
        "wind"
      ],
      "LTN": [
        "vis",
        "wind"
      ],
      "LGW": [
        "vis",
        "wind"
      ],
      "GDN": [
        "snow",
        "vis"
      ],
      "CTA": [
        "wind"
      ],
      "TGD": [
        "vis"
      ],
      "KUT": [
        "wind"
      ],
      "TZL": [
        "snow",
        "vis"
      ],
      "CRA": [
        "snow",
        "vis"
      ],
      "SBZ": [
        "snow",
        "vis"
      ],
      "VNO": [
        "vis",
        "wind"
      ],
      "POZ": [
        "snow",
        "vis"
      ],
      "WAW": [
        "snow"
      ],
      "SOF": [
        "snow",
        "vis"
      ],
      "BUD": [
        "snow"
      ],
      "CLJ": [
        "snow",
        "vis"
      ],
      "TGM": [
        "snow",
        "vis"
      ],
      "BTS": [
        "snow",
        "vis"
      ],
      "MXP": [
        "vis"
      ],
      "VAR": [
        "vis"
      ],
      "WRO": [
        "vis"
      ],
      "NAP": [],
      "PRG": [],
      "VIE": [],
      "KTW": [
        "vis"
      ],
      "WMI": [
        "vis"
      ],
      "IAS": [],
      "SCV": [],
      "RMO": []
    }
  },
  "lists": {
    "basesNow": [
      "BBU",
      "OTP",
      "KRK",
      "BEG",
      "TSR",
      "TIA",
      "FCO",
      "LTN",
      "LGW",
      "GDN",
      "CTA",
      "TGD",
      "KUT",
      "TZL",
      "CRA",
      "SBZ",
      "VNO",
      "POZ",
      "WAW",
      "SOF",
      "BUD",
      "CLJ",
      "TGM",
      "BTS",
      "MXP",
      "VAR",
      "WRO",
      "NAP",
      "PRG",
      "VIE",
      "KTW",
      "WMI",
      "IAS",
      "SCV",
      "RMO"
    ],
    "basesForecast": [
      "BBU",
      "OTP",
      "KRK",
      "BEG",
      "TSR",
      "FCO",
      "LTN",
      "LGW",
      "GDN",
      "CTA",
      "TGD",
      "KUT",
      "TZL",
      "CRA",
      "SBZ",
      "VNO",
      "POZ",
      "WAW",
      "SOF",
      "BUD",
      "CLJ",
      "TGM",
      "BTS",
      "MXP",
      "VAR",
      "WRO",
      "NAP",
      "PRG",
      "VIE",
      "KTW",
      "WMI"
    ],
    "basesAny": [
      "BBU",
      "OTP",
      "KRK",
      "BEG",
      "TSR",
      "TIA",
      "FCO",
      "LTN",
      "LGW",
      "GDN",
      "CTA",
      "TGD",
      "KUT",
      "TZL",
      "CRA",
      "SBZ",
      "VNO",
      "POZ",
      "WAW",
      "SOF",
      "BUD",
      "CLJ",
      "TGM",
      "BTS",
      "MXP",
      "VAR",
      "WRO",
      "NAP",
      "PRG",
      "VIE",
      "KTW",
      "WMI",
      "IAS",
      "SCV",
      "RMO"
    ],
    "baseTags": {
      "BBU": [
        "snow",
        "vis"
      ],
      "OTP": [
        "snow",
        "vis"
      ],
      "KRK": [
        "snow",
        "vis"
      ],
      "BEG": [
        "snow",
        "vis"
      ],
      "TSR": [
        "vis"
      ],
      "TIA": [],
      "FCO": [
        "wind"
      ],
      "LTN": [
        "vis",
        "wind"
      ],
      "LGW": [
        "vis",
        "wind"
      ],
      "GDN": [
        "snow",
        "vis"
      ],
      "CTA": [
        "wind"
      ],
      "TGD": [
        "vis"
      ],
      "KUT": [
        "wind"
      ],
      "TZL": [
        "snow",
        "vis"
      ],
      "CRA": [
        "snow",
        "vis"
      ],
      "SBZ": [
        "snow",
        "vis"
      ],
      "VNO": [
        "vis",
        "wind"
      ],
      "POZ": [
        "snow",
        "vis"
      ],
      "WAW": [
        "snow"
      ],
      "SOF": [
        "snow",
        "vis"
      ],
      "BUD": [
        "snow"
      ],
      "CLJ": [
        "snow",
        "vis"
      ],
      "TGM": [
        "snow",
        "vis"
      ],
      "BTS": [
        "snow",
        "vis"
      ],
      "MXP": [
        "vis"
      ],
      "VAR": [
        "vis"
      ],
      "WRO": [
        "vis"
      ],
      "NAP": [],
      "PRG": [],
      "VIE": [],
      "KTW": [
        "vis"
      ],
      "WMI": [
        "vis"
      ],
      "IAS": [],
      "SCV": [],
      "RMO": []
    },
    "engIceOps": [],
    "engIceOpsBases": [],
    "engIceOpsOut": []
  },
  "reasons": [
    "Bases impacted: 35",
    "ENG ICE OPS: 0",
    "NOW: 10 CRIT / 40 HIGH",
    "Top drivers: VIS/RVR+MINIMA, WIND/GUST, SNOW/CONTAM"
  ],
  "errors": []
}