{
  "generatedAt": "2026-02-16T19:54:38.792Z",
  "mode": "PROTECT",
  "nsi": 100,
  "trend": {
    "direction": "flat",
    "delta": 0
  },
  "counts": {
    "basesImpacted": 36,
    "nowCrit": 28,
    "nowHigh": 45,
    "nowMed": 35,
    "metCrit": 1,
    "tafCrit": 11,
    "engIceOpsCount": 0,
    "watchlistAirports": 159,
    "metarReturned": 157,
    "tafReturned": 158,
    "missingMetar": 2,
    "missingTaf": 1
  },
  "top": {
    "now": [
      "BER",
      "HAM",
      "HHN",
      "MST",
      "KRK",
      "KTW",
      "WMI",
      "POZ"
    ],
    "forecast": [
      "BER",
      "BRI",
      "BDS",
      "SUF",
      "CTA",
      "PMO",
      "MLA",
      "BBU"
    ]
  },
  "drivers": {
    "vis": 73,
    "wind": 61,
    "snow": 46,
    "icing": 0,
    "ts": 32
  },
  "details": {
    "baseTags": {
      "KRK": [
        "snow",
        "vis"
      ],
      "KTW": [
        "snow",
        "vis"
      ],
      "WMI": [
        "snow",
        "vis"
      ],
      "POZ": [
        "snow",
        "vis"
      ],
      "WAW": [
        "snow",
        "vis"
      ],
      "WRO": [
        "snow",
        "vis"
      ],
      "CTA": [
        "wind"
      ],
      "PRG": [
        "snow",
        "vis"
      ],
      "TZL": [
        "snow",
        "vis"
      ],
      "BBU": [
        "snow",
        "vis"
      ],
      "CRA": [
        "vis"
      ],
      "OTP": [
        "snow",
        "vis"
      ],
      "BEG": [
        "snow",
        "vis"
      ],
      "TGD": [
        "wind"
      ],
      "BTS": [
        "snow",
        "vis"
      ],
      "BUD": [
        "snow",
        "vis"
      ],
      "FCO": [
        "wind"
      ],
      "VIE": [
        "vis",
        "wind"
      ],
      "LTN": [
        "vis",
        "wind"
      ],
      "LGW": [
        "vis",
        "wind"
      ],
      "TIA": [],
      "NAP": [
        "wind"
      ],
      "VAR": [
        "vis"
      ],
      "KUT": [
        "wind"
      ],
      "GDN": [
        "snow"
      ],
      "SOF": [
        "snow",
        "vis"
      ],
      "CLJ": [
        "snow",
        "vis"
      ],
      "SBZ": [
        "snow",
        "vis"
      ],
      "VCE": [
        "vis"
      ],
      "TSR": [
        "vis"
      ],
      "SKP": [
        "vis"
      ],
      "VNO": [],
      "IAS": [],
      "SCV": [
        "vis"
      ],
      "TGM": [],
      "RMO": []
    }
  },
  "lists": {
    "basesNow": [
      "KRK",
      "KTW",
      "WMI",
      "POZ",
      "WAW",
      "WRO",
      "CTA",
      "PRG",
      "TZL",
      "BBU",
      "CRA",
      "OTP",
      "BEG",
      "TGD",
      "BTS",
      "BUD",
      "FCO",
      "VIE",
      "LTN",
      "LGW",
      "TIA",
      "NAP",
      "VAR",
      "KUT",
      "GDN",
      "SOF",
      "CLJ",
      "SBZ",
      "VCE",
      "TSR",
      "SKP",
      "VNO",
      "IAS",
      "SCV",
      "TGM",
      "RMO"
    ],
    "basesForecast": [
      "KRK",
      "KTW",
      "WMI",
      "POZ",
      "WAW",
      "WRO",
      "CTA",
      "PRG",
      "TZL",
      "BBU",
      "CRA",
      "OTP",
      "BEG",
      "TGD",
      "BTS",
      "BUD",
      "FCO",
      "VIE",
      "LTN",
      "LGW",
      "TIA",
      "NAP",
      "VAR",
      "GDN",
      "SOF",
      "CLJ",
      "SBZ",
      "VCE",
      "TSR",
      "SKP"
    ],
    "basesAny": [
      "KRK",
      "KTW",
      "WMI",
      "POZ",
      "WAW",
      "WRO",
      "CTA",
      "PRG",
      "TZL",
      "BBU",
      "CRA",
      "OTP",
      "BEG",
      "TGD",
      "BTS",
      "BUD",
      "FCO",
      "VIE",
      "LTN",
      "LGW",
      "TIA",
      "NAP",
      "VAR",
      "KUT",
      "GDN",
      "SOF",
      "CLJ",
      "SBZ",
      "VCE",
      "TSR",
      "SKP",
      "VNO",
      "IAS",
      "SCV",
      "TGM",
      "RMO"
    ],
    "baseTags": {
      "KRK": [
        "snow",
        "vis"
      ],
      "KTW": [
        "snow",
        "vis"
      ],
      "WMI": [
        "snow",
        "vis"
      ],
      "POZ": [
        "snow",
        "vis"
      ],
      "WAW": [
        "snow",
        "vis"
      ],
      "WRO": [
        "snow",
        "vis"
      ],
      "CTA": [
        "wind"
      ],
      "PRG": [
        "snow",
        "vis"
      ],
      "TZL": [
        "snow",
        "vis"
      ],
      "BBU": [
        "snow",
        "vis"
      ],
      "CRA": [
        "vis"
      ],
      "OTP": [
        "snow",
        "vis"
      ],
      "BEG": [
        "snow",
        "vis"
      ],
      "TGD": [
        "wind"
      ],
      "BTS": [
        "snow",
        "vis"
      ],
      "BUD": [
        "snow",
        "vis"
      ],
      "FCO": [
        "wind"
      ],
      "VIE": [
        "vis",
        "wind"
      ],
      "LTN": [
        "vis",
        "wind"
      ],
      "LGW": [
        "vis",
        "wind"
      ],
      "TIA": [],
      "NAP": [
        "wind"
      ],
      "VAR": [
        "vis"
      ],
      "KUT": [
        "wind"
      ],
      "GDN": [
        "snow"
      ],
      "SOF": [
        "snow",
        "vis"
      ],
      "CLJ": [
        "snow",
        "vis"
      ],
      "SBZ": [
        "snow",
        "vis"
      ],
      "VCE": [
        "vis"
      ],
      "TSR": [
        "vis"
      ],
      "SKP": [
        "vis"
      ],
      "VNO": [],
      "IAS": [],
      "SCV": [
        "vis"
      ],
      "TGM": [],
      "RMO": []
    },
    "engIceOps": [],
    "engIceOpsBases": [],
    "engIceOpsOut": []
  },
  "reasons": [
    "Bases impacted: 36",
    "ENG ICE OPS: 0",
    "NOW: 28 CRIT / 45 HIGH",
    "Top drivers: VIS/RVR+MINIMA, WIND/GUST, SNOW/CONTAM"
  ],
  "errors": []
}